design.v
// Code your design here
// Identifies the sequence 11101
// includes a overlap bit sequence as well
module jfsmMealyWithOverlap(dataout, clock, reset, datain);
  output reg dataout;
  input clock, reset, datain;
  
  reg[2:0] cs, ns;
  
  parameter a = 3'b000;
  parameter b = 3'b001;
  parameter c = 3'b010;
  parameter d = 3'b011;
  parameter e = 3'b100;
  parameter f = 3'b101;
  
  always @(posedge clock)
  begin
    if(reset)
      cs <= a;
    else
      cs <= ns;
  end

  always @(cs, datain)
  begin
    case(cs)
    a:
      begin
        if(datain)
          ns <= b;
        else
          ns <= a;
      end
    b:
      begin
        if(datain)
          ns <= c;
        else
          ns <= b;
      end
    c:
      begin
        if(datain)
          ns <= d;
        else
          ns <= a;
      end
    d:
      begin
        if(datain)
          ns <= d;
        else
          ns <= e;
      end
    e:
      begin
        if(datain)
          ns <= b; // This has to be ns <= a; if we have to consider with overlap
        else
          ns <= a;
      end
    endcase      
  end
  
  // This will assign the correct status to the dataout bit
  always @(cs, datain)
  begin
    if ( cs == e && datain == 1 )
      dataout <= 1;
    else
      dataout <= 0;
  end    
endmodule

testbench.v
// Code your testbench here
// or browse Examples
// the clock is manually controlled to set the inputs correctly
module jfsmMealyWithOverlapTb;
  wire dataout;
  reg clock, reset, datain;
  jfsmMealyWithOverlap jfsmM(dataout, clock, reset, datain);
  initial
  begin
    reset = 1; datain = 0; 
    clock = 1; #5; clock = 0; #5;
    reset = 0;
    clock = 1; #5; clock = 0; #5;
    
    $display("Starting input sequence");

    // we now make the 5 transistions and check the dataout to see if it is detected
    datain = 1; clock = 1; #5; clock = 0; #5;
    datain = 1; clock = 1; #5; clock = 0; #5;
    datain = 1; clock = 1; #5; clock = 0; #5;
    datain = 0; clock = 1; #5; clock = 0; #5;
    datain = 1; clock = 1; #5; clock = 0; #5;
    if ( dataout === 1 )
      $display("PASS %b", dataout);
    else
      $display("FAIL %b", dataout);
    
    // we now make the ONLY 4 transistions and check the dataout to see if it is detected
    //datain = 1; clock = 1; #5; clock = 0; #5;
    datain = 1; clock = 1; #5; clock = 0; #5;
    datain = 1; clock = 1; #5; clock = 0; #5;
    datain = 0; clock = 1; #5; clock = 0; #5;
    datain = 1; clock = 1; #5; clock = 0; #5;
    if ( dataout === 1 )
      $display("PASS %b", dataout);
    else
      $display("FAIL %b", dataout);
    
    // we now make a wrongsequence the 5 transistions and check the dataout to see if it is detected
    datain = 0; clock = 1; #5; clock = 0; #5;
    datain = 0; clock = 1; #5; clock = 0; #5;
    if ( dataout === 0 )
      $display("PASS %b", dataout);
    else
      $display("FAIL %b", dataout);
   
  end
    initial begin 
    $dumpfile("dump.vcd"); $dumpvars;
  end

endmodule

dump.vcd
$date
Wed Aug 28 03:28:28 2024
$end
$version
Riviera-PRO Version 2023.04.112.8911
$end
$timescale
1 ns
$end

$scope module jfsmMealyWithOverlapTb $end
$var wire 1 ! dataout $end
$var reg 1 " clock $end
$var reg 1 # reset $end
$var reg 1 $ datain $end

$scope module jfsmM $end
$var wire 1 % clock $end
$var wire 1 & reset $end
$var wire 1 ' datain $end
$var reg 1 ( dataout $end
$var reg 3 ) cs [2:0] $end
$var reg 3 * ns [2:0] $end
$var parameter 3 + a [2:0] $end
$var parameter 3 , b [2:0] $end
$var parameter 3 - c [2:0] $end
$var parameter 3 . d [2:0] $end
$var parameter 3 / e [2:0] $end
$var parameter 3 0 f [2:0] $end
$upscope $end

$upscope $end

$enddefinitions $end
$dumpvars
0!
1"
1#
0$
1%
1&
0'
0(
b0 )
b0 *
b0 +
b1 ,
b10 -
b11 .
b100 /
b101 0
$end
#5
0"
0%
#10
0#
1"
1%
0&
#15
0"
0%
#20
1$
1"
1%
1'
b1 *
#25
0"
0%
#30
1"
1%
b1 )
b10 *
#35
0"
0%
#40
1"
1%
b10 )
b11 *
#45
0"
0%
#50
0$
1"
1%
0'
b11 )
b0 *
b100 *
#55
0"
0%
#60
1$
1"
1%
1'
b100 )
b11 *
b1 *
1(
1!
#65
0"
0%
#70
1"
1%
b1 )
b10 *
0(
0!
#75
0"
0%
#80
1"
1%
b10 )
b11 *
#85
0"
0%
#90
0$
1"
1%
0'
b11 )
b0 *
b100 *
#95
0"
0%
#100
1$
1"
1%
1'
b100 )
b11 *
b1 *
1(
1!
#105
0"
0%
#110
0$
1"
1%
0'
b1 )
b0 *
0(
0!
b1 *
